{
"stores":[
  {"name":"Marketplace by Rustans", 
  "address":"B1, Central Square, 30th St., Taguig City",
  "coordinates":"5km away",
  "logo":"DDDDDDDDDDDDDDDDDD", 
  "contactNumbers":"000-001",
  "ratings":"5"},
  
  {"name":"S&R Membership", 
  "address":"32nd Street, 5th Ave, Taguig, 1634",
  "coordinates": "15km away",
  "logo":"AAAAAAAAAAAAAAAAAAA", 
  "contactNumbers":"000-001",
  "ratings":"5"},
  
  {"name":"Metro Supermarket", 
  "address":"L1, 169 Market! Market MAll, 26th Street COrner C5, BGC",
  "coordinates":"20km away",
  "logo":"gertrhh", 
  "contactNumbers":"000-001",
  "ratings":"5"},
  
  {"name":"SM HyperMarket", 
  "address":"SM Aura Premier, McKinley Pkwy, Taguig",
  "coordinates":"8km away",
  "logo":"tytruy", 
  "contactNumbers":"000-001",
  "ratings":"5"},
  
  {"name":"Robinsons Selections", 
  "address":"8 Formbes Town Center, Global Fort, Taguig City",
  "coordinates":"10km away",
  "logo":"ytyerui", 
  "contactNumbers":"000-001",
  "ratings":"5"},
]
}